matheusllopes_unique_package/__init__.py
matheusllopes_unique_package/module1_name/__init__.py
matheusllopes_unique_package/module1_name/file1_name.py
matheusllopes_unique_package/module1_name/file2_name.py
matheusllopes_unique_package/module2_name/__init__.py
matheusllopes_unique_package/module2_name/file1_name.py
matheusllopes_unique_package/module2_name/file2_name.py
matheusllopes_unique_package-0.0.2.dist-info/METADATA
matheusllopes_unique_package-0.0.2.dist-info/WHEEL
matheusllopes_unique_package-0.0.2.dist-info/top_level.txt
matheusllopes_unique_package-0.0.2.dist-info/RECORD
