Metadata-Version: 2.1
Name: matheusllopes-unique-package
Version: 0.0.2
Summary: My short description
Home-page: https://github.com/
Author: my_name
Author-email: matheusllopes22@gmail.com
License: UNKNOWN
Platform: UNKNOWN
Requires-Python: >=3.8
Requires-Dist: matplotlib
Requires-Dist: numpy
Requires-Dist: scikit-image (>=0.16.1)
